MANIFEST.in
README.md
setup.py
dexsdk/__init__.py
dexsdk/__main__.py
dexsdk/logger.py
dexsdk/main.py
dexsdk/pqconstant.py
dexsdk/version.py
dexsdk.egg-info/PKG-INFO
dexsdk.egg-info/SOURCES.txt
dexsdk.egg-info/dependency_links.txt
dexsdk.egg-info/entry_points.txt
dexsdk.egg-info/requires.txt
dexsdk.egg-info/top_level.txt
dexsdk/backtest/__init__.py
dexsdk/ccxtplus/__init__.py
dexsdk/enums/__init__.py
dexsdk/enums/orderStatus.py
dexsdk/interface/__init__.py
dexsdk/interface/abstractInstrument.py
dexsdk/interface/abstractOrder.py
dexsdk/interface/abstractPortfolio.py
dexsdk/interface/abstractPosition.py
dexsdk/interface/abstractRunInfo.py
dexsdk/interface/abstractStrategyContext.py
dexsdk/interface/abstractTrader.py
dexsdk/interface/constant.py
dexsdk/utils/__init__.py
dexsdk/utils/dynamic_import.py
dexsdk/utils/file_util.py
dexsdk/utils/import_global_modules.py
dexsdk/utils/threading_utils.py
dexsdk/utils/timer_factory.py
dexsdk/utils/value_type_util.py