Metadata-Version: 2.1
Name: dexsdk
Version: 0.0.1
Summary: SDK for stock analysis and strategy backtest.
Home-page: https://www.pinkquant.com
Author: PinkQuant
Author-email: pinkquant@163.com
Maintainer: topbip
Maintainer-email: pinkquant@163.com
Platform: all
Requires-Dist: Cython==3.0.11
Requires-Dist: plotly-express==0.4.1
Requires-Dist: msgpack>=0.4.7
Requires-Dist: pandas==1.5.2
Requires-Dist: python-dotenv==1.0.1
Requires-Dist: requests==2.31.0
Requires-Dist: six==1.16.0
Requires-Dist: thriftpy2==0.5.2
Requires-Dist: colorlog==4.8.0
Requires-Dist: QuantStats==0.0.62
Requires-Dist: ipython==8.12.2
Requires-Dist: numpy==1.24.4
Requires-Dist: tqdm==4.65.0
